console-msg/__init__.py
console-msg/alert_msgs.py
console-msg-jb/__init__.py
console-msg-jb/alert_msgs.py
console_msg_jb/__init__.py
console_msg_jb/alert_msgs.py
console_msg_jb-1.0.3.dist-info/METADATA
console_msg_jb-1.0.3.dist-info/WHEEL
console_msg_jb-1.0.3.dist-info/top_level.txt
console_msg_jb-1.0.3.dist-info/RECORD
