Metadata-Version: 2.4
Name: console-msg-jb
Version: 1.0.3
Summary: Imprime mensagens com cores personalizadas no terminal
Home-page: https://github.com/JBSilvaDev/console-msg
Author: JBSILVA
Author-email: jbsivla.dev@outlook.com
Requires-Python: >=3.8
Dynamic: author
Dynamic: author-email
Dynamic: description
Dynamic: description-content-type
Dynamic: home-page
Dynamic: requires-python
Dynamic: summary
